{
	"format_version": "1.26.0",
	"minecraft:block": {
		"description": {
			"identifier": "better_on_bedrock:voided_bush",
			"menu_category": {
				"category": "nature",
				"group": "itemGroup.name.leaves"
			}
		},
		"components": {
			"minecraft:geometry": {
				"identifier": "geometry.voided_bush",
				"culling": "better_on_bedrock:cube"
			},
			"minecraft:material_instances": {
				"*": {
					"texture": "voided_bush",
					"render_method": "alpha_test"
				}
			},
			
			"minecraft:map_color": "#7d7d7d",
			"minecraft:collision_box": false,
			"minecraft:selection_box": true,
			"minecraft:light_emission": 15,
			"minecraft:destructible_by_mining": {
				"seconds_to_destroy": 0.3
			},
			
			"minecraft:custom_components": [ "pog:tick" ],
			"minecraft:tick": {
                "interval_range": [ 130, 184 ]
            }
		}
	}
}