{
    "format_version": "1.21.0",
    "minecraft:weighted_random_feature": {
        "description": {
            "identifier": "better_on_bedrock:o_foliage/bluenerry_random_feature"
        },
        "features": [
            [
                "better_on_bedrock:o_foliage/blueberry_bush_1",
                5
            ],
            [
                "better_on_bedrock:o_foliage/blueberry_bush_2",
                5
            ],
            [
                "better_on_bedrock:o_foliage/blueberry_bush_3",
                4
            ],
            [
                "better_on_bedrock:o_foliage/blueberry_bush_4",
                3
            ]
        ]
    }
}