{
    "format_version": "1.21.60",
    "minecraft:block": {
        "description": {
            "identifier": "better_on_bedrock:onion_crop",
            "states": {
                "better_on_bedrock:growth_stage": {
                    "values": {
                        "min": 0,
                        "max": 3
                    }
                }
            }
        },
        "components": {
            "minecraft:geometry": "geometry.better_on_bedrock.cross",
            "minecraft:material_instances": {
                "*": {
                    "texture": "better_on_bedrock:onion_crop_stage_0",
                    "render_method": "alpha_test",
                    "ambient_occlusion": false,
                    "face_dimming": false
                }
            },
            "minecraft:liquid_detection": {
                "detection_rules": [
                    {
                        "can_contain_liquid": false,
                        "liquid_type": "water",
                        "on_liquid_touches": "popped"
                    }
                ]
            },
            "minecraft:loot": "loot_tables/blocks/crops/onion_lil.json",
            "minecraft:collision_box": false,
            "minecraft:selection_box": {
                "origin": [
                    -8,
                    0,
                    -8
                ],
                "size": [
                    16,
                    8,
                    16
                ]
            },
            "minecraft:placement_filter": {
                "conditions": [
                    {
                        "block_filter": [
                            "farmland"
                        ],
                        "allowed_faces": [
                            "up"
                        ]
                    }
                ]
            }
        },
        "permutations": [
            {
                "condition": "query.block_state('better_on_bedrock:growth_stage') == 0",
                "components": {
                    "minecraft:custom_components": [ "pog:ticking" ]
                }
            },
            {
                "condition": "query.block_state('better_on_bedrock:growth_stage') == 1",
                "components": {
                    "minecraft:material_instances": {
                        "*": {
                            "texture": "better_on_bedrock:onion_crop_stage_1",
                            "render_method": "alpha_test",
                            "ambient_occlusion": false,
                            "face_dimming": false
                        }
                    },
                    "minecraft:selection_box": {
                        "origin": [
                            -8,
                            0,
                            -8
                        ],
                        "size": [
                            16,
                            12,
                            16
                        ]
                    },
                    "minecraft:custom_components": [ "pog:ticking" ]
                }
            },
            {
                "condition": "query.block_state('better_on_bedrock:growth_stage') == 2",
                "components": {
                    "minecraft:material_instances": {
                        "*": {
                            "texture": "better_on_bedrock:onion_crop_stage_2",
                            "render_method": "alpha_test",
                            "ambient_occlusion": false,
                            "face_dimming": false
                        }
                    },
                    "minecraft:selection_box": {
                        "origin": [
                            -8,
                            0,
                            -8
                        ],
                        "size": [
                            16,
                            14,
                            16
                        ]
                    },
                    "minecraft:custom_components": [ "pog:ticking" ]
                }
            },
            {
                "condition": "query.block_state('better_on_bedrock:growth_stage') == 3",
                "components": {
                    "minecraft:material_instances": {
                        "*": {
                            "texture": "better_on_bedrock:onion_crop_stage_3",
                            "render_method": "alpha_test",
                            "ambient_occlusion": false,
                            "face_dimming": false
                        }
                    },
                    "minecraft:loot": "loot_tables/blocks/crops/onion.json",
                    "minecraft:selection_box": true
                }
            }
        ]
    }
}